db_broker/__init__.py
db_broker-0.0.1.dist-info/LICENSE
db_broker-0.0.1.dist-info/METADATA
db_broker-0.0.1.dist-info/WHEEL
db_broker-0.0.1.dist-info/top_level.txt
db_broker-0.0.1.dist-info/RECORD
