Metadata-Version: 2.1
Name: db-broker
Version: 0.0.1
Summary: UNKNOWN
Home-page: UNKNOWN
Author: jacob.h.barrow
Author-email: jacob.h.barrow@gmail.com
License: MIT
Platform: UNKNOWN
Classifier: License :: OSI Approved :: MIT License
Classifier: Programming Language :: Python
Classifier: Programming Language :: Python :: 3
License-File: LICENSE
Requires-Dist: SQLAlchemy
Requires-Dist: psycopg
